setup.py
hashlib/__init__.py
hashlib/_sha224.py
hashlib/_sha256.py
hashlib/_sha384.py
hashlib/_sha512.py
micropython_hashlib.egg-info/PKG-INFO
micropython_hashlib.egg-info/SOURCES.txt
micropython_hashlib.egg-info/dependency_links.txt
micropython_hashlib.egg-info/top_level.txt