Metadata-Version: 1.0
Name: micropython-hashlib
Version: 2.4.0.post4
Summary: PyPy hashlib module ported to MicroPython
Home-page: https://github.com/micropython/micropython-lib
Author: micropython-lib Developers
Author-email: micro-python@googlegroups.com
License: MIT
Platform: UNKNOWN
